{
  "project_info": {
    "project_number": "1055440469066",
    "firebase_url": "https://weatherapp-af4cb.firebaseio.com",
    "project_id": "weatherapp-af4cb",
    "storage_bucket": "weatherapp-af4cb.appspot.com"
  },
  "client": [
    {
      "client_info": {
        "mobilesdk_app_id": "1:1055440469066:android:5c5940e3d63ed283",
        "android_client_info": {
          "package_name": "com.example.weatherapp"
        }
      },
      "oauth_client": [
        {
          "client_id": "1055440469066-07bd09jvkjjnug9l2gfomcv7t1irpb0b.apps.googleusercontent.com",
          "client_type": 3
        }
      ],
      "api_key": [
        {
          "current_key": "AIzaSyBJXECN6V8svSxzAEstztfWauRebw_YkYo"
        }
      ],
      "services": {
        "appinvite_service": {
          "other_platform_oauth_client": [
            {
              "client_id": "1055440469066-07bd09jvkjjnug9l2gfomcv7t1irpb0b.apps.googleusercontent.com",
              "client_type": 3
            }
          ]
        }
      }
    }
  ],
  "configuration_version": "1"
}